{
	"dataVersion": 54,
	"connections": [
		{
			"autoConnect": true,
			"connectionName": "Rancilio2 NUC",
			"clientId": "HBwwiJGjsY",
			"host": "192.168.10.53",
			"port": 1883,
			"connectionType": "tcp",
			"defaultDashboard": "dashboard_1",
			"connectionTimeout": 30,
			"keepAlive": 60,
			"connectionId": "connection_4",
			"dashboards": [
				{
					"dashboardId": "dashboard_1",
					"dashboardName": "Rancilio PID",
					"dashboardPrefixTopic": "custom/K체che.Rancilio2/",
					"dashboardIcon": "cup_plate",
					"dashboardColor": "#2196F3",
					"panels": [
						{
							"noOfDivisor": 10,
							"maxPersistence": 100,
							"comboItemList": [
								{
									"color": "#08d800",
									"$$hashKey": "object:283",
									"topic": "temperature",
									"label": "Temperature",
									"showPoints": false,
									"showArea": false,
									"panelTopic": "custom/K체che.Rancilio2/temperature",
									"lineGraphData": [
										{
											"x": "2021-01-31T21:25:01.190Z",
											"y": 24.18
										},
										{
											"x": "2021-01-31T21:25:06.101Z",
											"y": 24.16
										},
										{
											"x": "2021-01-31T21:25:11.120Z",
											"y": 24.18
										},
										{
											"x": "2021-01-31T21:25:16.137Z",
											"y": 24.18
										},
										{
											"x": "2021-01-31T21:25:21.159Z",
											"y": 24.18
										},
										{
											"x": "2021-01-31T21:25:26.176Z",
											"y": 24.2
										},
										{
											"x": "2021-01-31T21:25:31.187Z",
											"y": 24.18
										},
										{
											"x": "2021-01-31T21:25:36.068Z",
											"y": 24.18
										},
										{
											"x": "2021-01-31T21:25:41.125Z",
											"y": 24.12
										},
										{
											"x": "2021-01-31T21:25:46.144Z",
											"y": 24.16
										},
										{
											"x": "2021-01-31T21:25:51.161Z",
											"y": 24.14
										},
										{
											"x": "2021-01-31T21:25:56.178Z",
											"y": 24.16
										},
										{
											"x": "2021-01-31T21:26:01.194Z",
											"y": 24.16
										},
										{
											"x": "2021-01-31T21:26:06.110Z",
											"y": 24.16
										},
										{
											"x": "2021-01-31T21:26:11.131Z",
											"y": 24.14
										},
										{
											"x": "2021-01-31T21:26:16.147Z",
											"y": 24.12
										},
										{
											"x": "2021-01-31T21:26:21.159Z",
											"y": 24.1
										},
										{
											"x": "2021-01-31T21:26:26.180Z",
											"y": 24.1
										},
										{
											"x": "2021-01-31T21:26:31.097Z",
											"y": 24.12
										},
										{
											"x": "2021-01-31T21:26:36.116Z",
											"y": 24.1
										},
										{
											"x": "2021-01-31T21:26:41.133Z",
											"y": 24.1
										},
										{
											"x": "2021-01-31T21:26:46.151Z",
											"y": 24.1
										},
										{
											"x": "2021-01-31T21:26:51.166Z",
											"y": 24.1
										},
										{
											"x": "2021-01-31T21:26:56.185Z",
											"y": 24.1
										},
										{
											"x": "2021-01-31T21:27:01.101Z",
											"y": 24.1
										},
										{
											"x": "2021-01-31T21:27:06.118Z",
											"y": 24.1
										},
										{
											"x": "2021-01-31T21:27:11.135Z",
											"y": 24.1
										},
										{
											"x": "2021-01-31T21:27:16.068Z",
											"y": 24.1
										},
										{
											"x": "2021-01-31T21:27:21.172Z",
											"y": 24.1
										},
										{
											"x": "2021-01-31T21:27:26.190Z",
											"y": 24.1
										},
										{
											"x": "2021-01-31T21:27:31.071Z",
											"y": 24.1
										},
										{
											"x": "2021-01-31T21:27:36.069Z",
											"y": 24.1
										},
										{
											"x": "2021-01-31T21:27:41.136Z",
											"y": 24.1
										},
										{
											"x": "2021-01-31T21:27:46.158Z",
											"y": 24.1
										},
										{
											"x": "2021-01-31T21:27:51.175Z",
											"y": 24.1
										},
										{
											"x": "2021-01-31T21:27:56.070Z",
											"y": 24.1
										},
										{
											"x": "2021-01-31T21:28:01.106Z",
											"y": 24.1
										},
										{
											"x": "2021-01-31T21:28:06.126Z",
											"y": 24.1
										},
										{
											"x": "2021-01-31T21:28:49.851Z",
											"y": 24.1
										},
										{
											"x": "2021-01-31T21:28:54.867Z",
											"y": 24.1
										},
										{
											"x": "2021-01-31T21:28:59.881Z",
											"y": 24.04
										},
										{
											"x": "2021-01-31T21:29:04.902Z",
											"y": 24.06
										},
										{
											"x": "2021-01-31T21:29:09.821Z",
											"y": 24.1
										},
										{
											"x": "2021-01-31T21:29:14.836Z",
											"y": 24.02
										},
										{
											"x": "2021-01-31T21:29:19.853Z",
											"y": 24.02
										},
										{
											"x": "2021-01-31T21:29:24.871Z",
											"y": 24
										},
										{
											"x": "2021-01-31T21:29:29.888Z",
											"y": 24
										},
										{
											"x": "2021-01-31T21:29:34.907Z",
											"y": 24.04
										},
										{
											"x": "2021-01-31T21:29:39.822Z",
											"y": 24.04
										},
										{
											"x": "2021-01-31T21:29:44.840Z",
											"y": 24
										},
										{
											"x": "2021-01-31T21:29:49.850Z",
											"y": 24
										},
										{
											"x": "2021-01-31T21:29:54.871Z",
											"y": 24
										},
										{
											"x": "2021-01-31T21:29:59.874Z",
											"y": 24
										},
										{
											"x": "2021-01-31T21:30:04.893Z",
											"y": 24.02
										},
										{
											"x": "2021-01-31T21:30:09.824Z",
											"y": 24.02
										},
										{
											"x": "2021-01-31T21:30:14.843Z",
											"y": 24
										},
										{
											"x": "2021-01-31T21:30:19.860Z",
											"y": 24.04
										},
										{
											"x": "2021-01-31T21:30:24.878Z",
											"y": 24.02
										},
										{
											"x": "2021-01-31T21:30:29.896Z",
											"y": 24
										},
										{
											"x": "2021-01-31T21:30:34.913Z",
											"y": 24
										},
										{
											"x": "2021-01-31T21:30:39.830Z",
											"y": 24.02
										},
										{
											"x": "2021-01-31T21:30:44.843Z",
											"y": 24
										},
										{
											"x": "2021-01-31T21:30:49.862Z",
											"y": 24.02
										},
										{
											"x": "2021-01-31T21:30:54.878Z",
											"y": 24.02
										},
										{
											"x": "2021-01-31T21:30:59.896Z",
											"y": 24
										},
										{
											"x": "2021-01-31T21:31:04.815Z",
											"y": 24.02
										},
										{
											"x": "2021-01-31T21:31:09.834Z",
											"y": 24
										},
										{
											"x": "2021-01-31T21:31:14.979Z",
											"y": 24
										},
										{
											"x": "2021-01-31T21:31:20.001Z",
											"y": 24
										},
										{
											"x": "2021-01-31T21:31:24.887Z",
											"y": 24
										},
										{
											"x": "2021-01-31T21:31:30.147Z",
											"y": 24
										},
										{
											"x": "2021-01-31T21:31:34.940Z",
											"y": 24
										},
										{
											"x": "2021-01-31T21:31:39.946Z",
											"y": 24
										},
										{
											"x": "2021-01-31T21:31:44.962Z",
											"y": 23.92
										},
										{
											"x": "2021-01-31T21:31:49.962Z",
											"y": 23.96
										},
										{
											"x": "2021-01-31T21:31:55.024Z",
											"y": 23.98
										},
										{
											"x": "2021-01-31T21:32:00.006Z",
											"y": 24
										},
										{
											"x": "2021-01-31T21:32:04.947Z",
											"y": 23.96
										},
										{
											"x": "2021-01-31T21:32:09.981Z",
											"y": 23.94
										},
										{
											"x": "2021-01-31T21:32:14.983Z",
											"y": 24
										},
										{
											"x": "2021-01-31T21:32:20.017Z",
											"y": 23.96
										},
										{
											"x": "2021-01-31T21:32:25.227Z",
											"y": 23.9
										},
										{
											"x": "2021-01-31T21:32:30.040Z",
											"y": 23.92
										},
										{
											"x": "2021-01-31T21:32:34.958Z",
											"y": 23.94
										},
										{
											"x": "2021-01-31T21:33:52.726Z",
											"y": 23.9
										},
										{
											"x": "2021-01-31T21:33:55.039Z",
											"y": 23.9
										},
										{
											"x": "2021-01-31T21:33:59.944Z",
											"y": 23.9
										},
										{
											"x": "2021-01-31T21:34:05.076Z",
											"y": 23.9
										},
										{
											"x": "2021-01-31T21:34:09.949Z",
											"y": 23.9
										},
										{
											"x": "2021-01-31T21:34:15.004Z",
											"y": 23.9
										},
										{
											"x": "2021-01-31T21:34:20.015Z",
											"y": 23.9
										},
										{
											"x": "2021-01-31T21:34:25.030Z",
											"y": 23.9
										},
										{
											"x": "2021-01-31T21:34:30.021Z",
											"y": 23.9
										},
										{
											"x": "2021-01-31T21:34:35.069Z",
											"y": 23.9
										},
										{
											"x": "2021-01-31T21:34:39.990Z",
											"y": 23.9
										},
										{
											"x": "2021-01-31T21:34:45.102Z",
											"y": 23.9
										},
										{
											"x": "2021-01-31T21:34:50.139Z",
											"y": 23.9
										},
										{
											"x": "2021-01-31T21:34:55.111Z",
											"y": 23.9
										},
										{
											"x": "2021-01-31T21:35:55.740Z",
											"y": 23.9
										},
										{
											"x": "2021-01-31T21:36:00.961Z",
											"y": 23.9
										},
										{
											"x": "2021-01-31T21:44:10.238Z",
											"y": 23.2
										},
										{
											"x": "2021-01-31T21:44:15.239Z",
											"y": 23.2
										},
										{
											"x": "2021-01-31T21:44:20.243Z",
											"y": 23.2
										},
										{
											"x": "2021-01-31T21:44:25.278Z",
											"y": 23.2
										},
										{
											"x": "2021-01-31T21:44:30.300Z",
											"y": 23.2
										},
										{
											"x": "2021-01-31T21:44:35.318Z",
											"y": 23.18
										},
										{
											"x": "2021-01-31T21:44:40.336Z",
											"y": 23.18
										},
										{
											"x": "2021-01-31T21:44:45.239Z",
											"y": 23.16
										},
										{
											"x": "2021-01-31T21:44:50.265Z",
											"y": 23.18
										},
										{
											"x": "2021-01-31T21:44:55.286Z",
											"y": 23.18
										},
										{
											"x": "2021-01-31T21:45:00.304Z",
											"y": 23.16
										},
										{
											"x": "2021-01-31T21:45:05.322Z",
											"y": 23.14
										},
										{
											"x": "2021-01-31T21:45:10.340Z",
											"y": 23.12
										},
										{
											"x": "2021-01-31T21:45:15.356Z",
											"y": 23.1
										},
										{
											"x": "2021-01-31T21:45:20.272Z",
											"y": 23.12
										},
										{
											"x": "2021-01-31T21:45:25.291Z",
											"y": 23.12
										},
										{
											"x": "2021-01-31T21:45:30.308Z",
											"y": 23.12
										},
										{
											"x": "2021-01-31T21:45:35.328Z",
											"y": 23.14
										},
										{
											"x": "2021-01-31T21:45:40.344Z",
											"y": 23.14
										},
										{
											"x": "2021-01-31T21:45:45.360Z",
											"y": 23.12
										},
										{
											"x": "2021-01-31T21:45:50.277Z",
											"y": 23.1
										},
										{
											"x": "2021-01-31T21:45:55.293Z",
											"y": 23.1
										},
										{
											"x": "2021-01-31T21:46:00.312Z",
											"y": 23.1
										},
										{
											"x": "2021-01-31T21:46:05.331Z",
											"y": 23.1
										},
										{
											"x": "2021-01-31T21:46:10.347Z",
											"y": 23.1
										},
										{
											"x": "2021-01-31T21:46:15.361Z",
											"y": 23.1
										},
										{
											"x": "2021-01-31T21:46:20.280Z",
											"y": 23.1
										},
										{
											"x": "2021-01-31T21:46:25.297Z",
											"y": 23.1
										},
										{
											"x": "2021-01-31T21:46:30.319Z",
											"y": 23.1
										},
										{
											"x": "2021-01-31T21:46:35.332Z",
											"y": 23.1
										},
										{
											"x": "2021-01-31T21:46:40.348Z",
											"y": 23.1
										},
										{
											"x": "2021-01-31T21:46:45.369Z",
											"y": 23.1
										},
										{
											"x": "2021-01-31T21:46:50.387Z",
											"y": 23.1
										},
										{
											"x": "2021-01-31T21:46:55.301Z",
											"y": 23.1
										},
										{
											"x": "2021-01-31T21:47:00.320Z",
											"y": 23.1
										},
										{
											"x": "2021-01-31T21:47:05.332Z",
											"y": 23.1
										},
										{
											"x": "2021-01-31T21:47:10.354Z",
											"y": 23.1
										},
										{
											"x": "2021-01-31T21:47:15.268Z",
											"y": 23.1
										},
										{
											"x": "2021-01-31T21:47:20.288Z",
											"y": 23.1
										},
										{
											"x": "2021-01-31T21:47:25.305Z",
											"y": 23.1
										},
										{
											"x": "2021-01-31T21:47:30.322Z",
											"y": 23.1
										},
										{
											"x": "2021-01-31T21:47:35.338Z",
											"y": 23.1
										},
										{
											"x": "2021-01-31T21:47:40.359Z",
											"y": 23.1
										},
										{
											"x": "2021-01-31T21:47:45.275Z",
											"y": 23.1
										},
										{
											"x": "2021-01-31T21:47:50.291Z",
											"y": 23.1
										},
										{
											"x": "2021-01-31T21:47:55.310Z",
											"y": 23.1
										},
										{
											"x": "2021-01-31T21:48:00.454Z",
											"y": 23.06
										},
										{
											"x": "2021-01-31T21:48:05.479Z",
											"y": 23.1
										},
										{
											"x": "2021-01-31T21:48:10.506Z",
											"y": 23.1
										},
										{
											"x": "2021-01-31T21:48:15.484Z",
											"y": 23.08
										},
										{
											"x": "2021-01-31T21:48:20.536Z",
											"y": 23.1
										},
										{
											"x": "2021-01-31T21:48:25.449Z",
											"y": 23.1
										},
										{
											"x": "2021-01-31T21:48:30.450Z",
											"y": 23.1
										},
										{
											"x": "2021-01-31T21:48:35.343Z",
											"y": 23.1
										},
										{
											"x": "2021-01-31T21:48:40.364Z",
											"y": 23.06
										},
										{
											"x": "2021-01-31T21:49:22.658Z",
											"y": 23.04
										},
										{
											"x": "2021-01-31T21:49:27.673Z",
											"y": 23.02
										},
										{
											"x": "2021-01-31T21:49:32.587Z",
											"y": 23
										},
										{
											"x": "2021-01-31T21:49:37.604Z",
											"y": 23
										},
										{
											"x": "2021-01-31T21:49:42.621Z",
											"y": 23
										},
										{
											"x": "2021-01-31T21:49:47.642Z",
											"y": 23
										},
										{
											"x": "2021-01-31T21:49:52.661Z",
											"y": 23
										},
										{
											"x": "2021-01-31T21:49:57.676Z",
											"y": 23
										},
										{
											"x": "2021-01-31T21:50:02.591Z",
											"y": 23
										},
										{
											"x": "2021-01-31T21:50:07.611Z",
											"y": 23
										},
										{
											"x": "2021-01-31T21:50:12.631Z",
											"y": 23
										},
										{
											"x": "2021-01-31T21:50:17.644Z",
											"y": 23
										},
										{
											"x": "2021-01-31T21:50:22.664Z",
											"y": 23
										},
										{
											"x": "2021-01-31T21:50:27.680Z",
											"y": 23
										},
										{
											"x": "2021-01-31T21:50:32.596Z",
											"y": 23
										},
										{
											"x": "2021-01-31T21:50:37.614Z",
											"y": 23
										},
										{
											"x": "2021-01-31T21:50:42.631Z",
											"y": 23
										},
										{
											"x": "2021-01-31T21:50:47.647Z",
											"y": 23
										},
										{
											"x": "2021-01-31T21:50:52.668Z",
											"y": 23
										},
										{
											"x": "2021-01-31T21:50:57.683Z",
											"y": 23
										},
										{
											"x": "2021-01-31T21:51:02.600Z",
											"y": 23
										},
										{
											"x": "2021-01-31T21:51:07.618Z",
											"y": 22.98
										},
										{
											"x": "2021-01-31T21:51:12.635Z",
											"y": 23
										},
										{
											"x": "2021-01-31T21:51:17.652Z",
											"y": 22.96
										},
										{
											"x": "2021-01-31T21:51:22.670Z",
											"y": 22.98
										},
										{
											"x": "2021-01-31T21:51:27.686Z",
											"y": 22.98
										},
										{
											"x": "2021-01-31T21:51:32.606Z",
											"y": 22.96
										},
										{
											"x": "2021-01-31T21:51:37.620Z",
											"y": 22.96
										},
										{
											"x": "2021-01-31T21:51:42.634Z",
											"y": 23
										},
										{
											"x": "2021-01-31T21:51:47.655Z",
											"y": 22.96
										},
										{
											"x": "2021-01-31T21:51:52.672Z",
											"y": 22.98
										},
										{
											"x": "2021-01-31T21:51:57.590Z",
											"y": 22.92
										},
										{
											"x": "2021-01-31T21:52:02.852Z",
											"y": 22.92
										},
										{
											"x": "2021-01-31T21:52:07.867Z",
											"y": 22.92
										},
										{
											"x": "2021-01-31T21:52:12.737Z",
											"y": 22.96
										},
										{
											"x": "2021-01-31T21:52:17.908Z",
											"y": 22.94
										},
										{
											"x": "2021-01-31T21:52:22.915Z",
											"y": 22.94
										},
										{
											"x": "2021-01-31T21:52:27.676Z",
											"y": 22.94
										},
										{
											"x": "2021-01-31T21:52:32.600Z",
											"y": 22.92
										},
										{
											"x": "2021-01-31T21:52:37.720Z",
											"y": 22.9
										},
										{
											"x": "2021-01-31T21:52:42.651Z",
											"y": 22.9
										},
										{
											"x": "2021-01-31T21:52:47.910Z",
											"y": 22.9
										},
										{
											"x": "2021-01-31T21:52:52.796Z",
											"y": 22.94
										},
										{
											"x": "2021-01-31T21:52:57.843Z",
											"y": 22.9
										},
										{
											"x": "2021-01-31T21:53:02.798Z",
											"y": 22.9
										},
										{
											"x": "2021-01-31T21:53:07.772Z",
											"y": 22.9
										},
										{
											"x": "2021-01-31T21:53:12.891Z",
											"y": 22.92
										},
										{
											"x": "2021-01-31T21:53:17.810Z",
											"y": 22.9
										},
										{
											"x": "2021-01-31T21:53:22.825Z",
											"y": 22.9
										},
										{
											"x": "2021-01-31T21:53:27.562Z",
											"y": 22.9
										},
										{
											"x": "2021-01-31T21:53:32.718Z",
											"y": 22.9
										},
										{
											"x": "2021-01-31T21:53:37.762Z",
											"y": 22.9
										},
										{
											"x": "2021-01-31T21:53:42.877Z",
											"y": 22.9
										},
										{
											"x": "2021-01-31T21:53:47.897Z",
											"y": 22.9
										},
										{
											"x": "2021-01-31T21:53:52.821Z",
											"y": 22.9
										},
										{
											"x": "2021-01-31T21:53:57.790Z",
											"y": 22.9
										},
										{
											"x": "2021-01-31T21:54:02.757Z",
											"y": 22.9
										},
										{
											"x": "2021-01-31T21:54:07.879Z",
											"y": 22.9
										},
										{
											"x": "2021-01-31T21:54:12.651Z",
											"y": 22.9
										},
										{
											"x": "2021-01-31T21:54:17.666Z",
											"y": 22.9
										}
									]
								},
								{
									"color": "#ec473a",
									"$$hashKey": "object:7021",
									"topic": "heaterUtilization",
									"label": "HeaterUtilization",
									"showArea": true,
									"panelTopic": "custom/K체che.Rancilio2/heaterUtilization",
									"lineGraphData": [
										{
											"x": "2021-01-31T21:24:56.188Z",
											"y": 100
										},
										{
											"x": "2021-01-31T21:25:01.201Z",
											"y": 100
										},
										{
											"x": "2021-01-31T21:25:06.111Z",
											"y": 100
										},
										{
											"x": "2021-01-31T21:25:11.131Z",
											"y": 100
										},
										{
											"x": "2021-01-31T21:25:16.145Z",
											"y": 100
										},
										{
											"x": "2021-01-31T21:25:21.175Z",
											"y": 100
										},
										{
											"x": "2021-01-31T21:25:26.195Z",
											"y": 100
										},
										{
											"x": "2021-01-31T21:25:31.197Z",
											"y": 100
										},
										{
											"x": "2021-01-31T21:25:36.112Z",
											"y": 100
										},
										{
											"x": "2021-01-31T21:25:41.144Z",
											"y": 100
										},
										{
											"x": "2021-01-31T21:25:46.162Z",
											"y": 100
										},
										{
											"x": "2021-01-31T21:25:51.172Z",
											"y": 100
										},
										{
											"x": "2021-01-31T21:25:56.195Z",
											"y": 100
										},
										{
											"x": "2021-01-31T21:26:01.213Z",
											"y": 100
										},
										{
											"x": "2021-01-31T21:26:06.131Z",
											"y": 100
										},
										{
											"x": "2021-01-31T21:26:11.160Z",
											"y": 100
										},
										{
											"x": "2021-01-31T21:26:16.165Z",
											"y": 100
										},
										{
											"x": "2021-01-31T21:26:21.176Z",
											"y": 100
										},
										{
											"x": "2021-01-31T21:26:26.194Z",
											"y": 100
										},
										{
											"x": "2021-01-31T21:26:31.123Z",
											"y": 100
										},
										{
											"x": "2021-01-31T21:26:36.135Z",
											"y": 100
										},
										{
											"x": "2021-01-31T21:26:41.152Z",
											"y": 100
										},
										{
											"x": "2021-01-31T21:26:46.167Z",
											"y": 100
										},
										{
											"x": "2021-01-31T21:26:51.184Z",
											"y": 100
										},
										{
											"x": "2021-01-31T21:26:56.197Z",
											"y": 100
										},
										{
											"x": "2021-01-31T21:27:01.130Z",
											"y": 100
										},
										{
											"x": "2021-01-31T21:27:06.135Z",
											"y": 100
										},
										{
											"x": "2021-01-31T21:27:11.155Z",
											"y": 100
										},
										{
											"x": "2021-01-31T21:27:16.079Z",
											"y": 100
										},
										{
											"x": "2021-01-31T21:27:21.190Z",
											"y": 100
										},
										{
											"x": "2021-01-31T21:27:26.207Z",
											"y": 100
										},
										{
											"x": "2021-01-31T21:27:31.093Z",
											"y": 100
										},
										{
											"x": "2021-01-31T21:27:36.094Z",
											"y": 100
										},
										{
											"x": "2021-01-31T21:27:41.150Z",
											"y": 100
										},
										{
											"x": "2021-01-31T21:27:46.170Z",
											"y": 100
										},
										{
											"x": "2021-01-31T21:27:51.188Z",
											"y": 100
										},
										{
											"x": "2021-01-31T21:27:56.116Z",
											"y": 100
										},
										{
											"x": "2021-01-31T21:28:01.130Z",
											"y": 100
										},
										{
											"x": "2021-01-31T21:28:06.146Z",
											"y": 100
										},
										{
											"x": "2021-01-31T21:28:49.868Z",
											"y": 100
										},
										{
											"x": "2021-01-31T21:28:54.886Z",
											"y": 100
										},
										{
											"x": "2021-01-31T21:28:59.907Z",
											"y": 100
										},
										{
											"x": "2021-01-31T21:29:04.930Z",
											"y": 100
										},
										{
											"x": "2021-01-31T21:29:09.844Z",
											"y": 100
										},
										{
											"x": "2021-01-31T21:29:14.859Z",
											"y": 100
										},
										{
											"x": "2021-01-31T21:29:19.876Z",
											"y": 100
										},
										{
											"x": "2021-01-31T21:29:24.895Z",
											"y": 100
										},
										{
											"x": "2021-01-31T21:29:29.915Z",
											"y": 100
										},
										{
											"x": "2021-01-31T21:29:34.936Z",
											"y": 100
										},
										{
											"x": "2021-01-31T21:29:39.839Z",
											"y": 100
										},
										{
											"x": "2021-01-31T21:29:44.865Z",
											"y": 100
										},
										{
											"x": "2021-01-31T21:29:49.870Z",
											"y": 100
										},
										{
											"x": "2021-01-31T21:29:54.895Z",
											"y": 100
										},
										{
											"x": "2021-01-31T21:29:59.890Z",
											"y": 100
										},
										{
											"x": "2021-01-31T21:30:04.925Z",
											"y": 100
										},
										{
											"x": "2021-01-31T21:30:09.849Z",
											"y": 100
										},
										{
											"x": "2021-01-31T21:30:14.862Z",
											"y": 100
										},
										{
											"x": "2021-01-31T21:30:19.875Z",
											"y": 100
										},
										{
											"x": "2021-01-31T21:30:24.898Z",
											"y": 100
										},
										{
											"x": "2021-01-31T21:30:29.910Z",
											"y": 100
										},
										{
											"x": "2021-01-31T21:30:34.921Z",
											"y": 100
										},
										{
											"x": "2021-01-31T21:30:39.848Z",
											"y": 100
										},
										{
											"x": "2021-01-31T21:30:44.868Z",
											"y": 100
										},
										{
											"x": "2021-01-31T21:30:49.886Z",
											"y": 100
										},
										{
											"x": "2021-01-31T21:30:54.891Z",
											"y": 100
										},
										{
											"x": "2021-01-31T21:30:59.922Z",
											"y": 100
										},
										{
											"x": "2021-01-31T21:31:04.841Z",
											"y": 100
										},
										{
											"x": "2021-01-31T21:31:09.854Z",
											"y": 100
										},
										{
											"x": "2021-01-31T21:31:15.007Z",
											"y": 100
										},
										{
											"x": "2021-01-31T21:31:20.022Z",
											"y": 100
										},
										{
											"x": "2021-01-31T21:31:24.911Z",
											"y": 100
										},
										{
											"x": "2021-01-31T21:31:30.168Z",
											"y": 100
										},
										{
											"x": "2021-01-31T21:31:34.964Z",
											"y": 100
										},
										{
											"x": "2021-01-31T21:31:39.962Z",
											"y": 100
										},
										{
											"x": "2021-01-31T21:31:44.978Z",
											"y": 100
										},
										{
											"x": "2021-01-31T21:31:49.975Z",
											"y": 100
										},
										{
											"x": "2021-01-31T21:31:55.044Z",
											"y": 100
										},
										{
											"x": "2021-01-31T21:32:00.019Z",
											"y": 100
										},
										{
											"x": "2021-01-31T21:32:04.966Z",
											"y": 100
										},
										{
											"x": "2021-01-31T21:32:10.000Z",
											"y": 100
										},
										{
											"x": "2021-01-31T21:32:15.018Z",
											"y": 100
										},
										{
											"x": "2021-01-31T21:32:20.048Z",
											"y": 100
										},
										{
											"x": "2021-01-31T21:32:25.248Z",
											"y": 100
										},
										{
											"x": "2021-01-31T21:32:30.064Z",
											"y": 100
										},
										{
											"x": "2021-01-31T21:32:34.989Z",
											"y": 100
										},
										{
											"x": "2021-01-31T21:33:55.061Z",
											"y": 100
										},
										{
											"x": "2021-01-31T21:33:59.963Z",
											"y": 100
										},
										{
											"x": "2021-01-31T21:34:05.096Z",
											"y": 100
										},
										{
											"x": "2021-01-31T21:34:09.963Z",
											"y": 100
										},
										{
											"x": "2021-01-31T21:34:15.026Z",
											"y": 100
										},
										{
											"x": "2021-01-31T21:34:20.032Z",
											"y": 100
										},
										{
											"x": "2021-01-31T21:34:25.050Z",
											"y": 100
										},
										{
											"x": "2021-01-31T21:34:30.033Z",
											"y": 100
										},
										{
											"x": "2021-01-31T21:34:35.087Z",
											"y": 100
										},
										{
											"x": "2021-01-31T21:34:40.011Z",
											"y": 100
										},
										{
											"x": "2021-01-31T21:34:45.121Z",
											"y": 100
										},
										{
											"x": "2021-01-31T21:34:50.160Z",
											"y": 100
										},
										{
											"x": "2021-01-31T21:34:55.126Z",
											"y": 100
										},
										{
											"x": "2021-01-31T21:35:55.767Z",
											"y": 100
										},
										{
											"x": "2021-01-31T21:36:00.977Z",
											"y": 100
										},
										{
											"x": "2021-01-31T21:44:10.248Z",
											"y": 100
										},
										{
											"x": "2021-01-31T21:44:15.250Z",
											"y": 100
										},
										{
											"x": "2021-01-31T21:44:20.251Z",
											"y": 100
										},
										{
											"x": "2021-01-31T21:44:25.290Z",
											"y": 100
										},
										{
											"x": "2021-01-31T21:44:30.310Z",
											"y": 100
										},
										{
											"x": "2021-01-31T21:44:35.331Z",
											"y": 100
										},
										{
											"x": "2021-01-31T21:44:40.351Z",
											"y": 100
										},
										{
											"x": "2021-01-31T21:44:45.256Z",
											"y": 100
										},
										{
											"x": "2021-01-31T21:44:50.285Z",
											"y": 100
										},
										{
											"x": "2021-01-31T21:44:55.298Z",
											"y": 100
										},
										{
											"x": "2021-01-31T21:45:00.316Z",
											"y": 100
										},
										{
											"x": "2021-01-31T21:45:05.337Z",
											"y": 100
										},
										{
											"x": "2021-01-31T21:45:10.362Z",
											"y": 100
										},
										{
											"x": "2021-01-31T21:45:15.371Z",
											"y": 100
										},
										{
											"x": "2021-01-31T21:45:20.300Z",
											"y": 100
										},
										{
											"x": "2021-01-31T21:45:25.308Z",
											"y": 100
										},
										{
											"x": "2021-01-31T21:45:30.334Z",
											"y": 100
										},
										{
											"x": "2021-01-31T21:45:35.344Z",
											"y": 100
										},
										{
											"x": "2021-01-31T21:45:40.370Z",
											"y": 100
										},
										{
											"x": "2021-01-31T21:45:45.377Z",
											"y": 100
										},
										{
											"x": "2021-01-31T21:45:50.299Z",
											"y": 100
										},
										{
											"x": "2021-01-31T21:45:55.311Z",
											"y": 100
										},
										{
											"x": "2021-01-31T21:46:00.338Z",
											"y": 100
										},
										{
											"x": "2021-01-31T21:46:05.358Z",
											"y": 100
										},
										{
											"x": "2021-01-31T21:46:10.368Z",
											"y": 100
										},
										{
											"x": "2021-01-31T21:46:15.379Z",
											"y": 100
										},
										{
											"x": "2021-01-31T21:46:20.309Z",
											"y": 100
										},
										{
											"x": "2021-01-31T21:46:25.325Z",
											"y": 100
										},
										{
											"x": "2021-01-31T21:46:30.336Z",
											"y": 100
										},
										{
											"x": "2021-01-31T21:46:35.351Z",
											"y": 100
										},
										{
											"x": "2021-01-31T21:46:40.375Z",
											"y": 100
										},
										{
											"x": "2021-01-31T21:46:45.394Z",
											"y": 100
										},
										{
											"x": "2021-01-31T21:46:50.413Z",
											"y": 100
										},
										{
											"x": "2021-01-31T21:46:55.324Z",
											"y": 100
										},
										{
											"x": "2021-01-31T21:47:00.347Z",
											"y": 100
										},
										{
											"x": "2021-01-31T21:47:05.356Z",
											"y": 100
										},
										{
											"x": "2021-01-31T21:47:10.370Z",
											"y": 100
										},
										{
											"x": "2021-01-31T21:47:15.293Z",
											"y": 100
										},
										{
											"x": "2021-01-31T21:47:20.319Z",
											"y": 100
										},
										{
											"x": "2021-01-31T21:47:25.364Z",
											"y": 100
										},
										{
											"x": "2021-01-31T21:47:30.347Z",
											"y": 100
										},
										{
											"x": "2021-01-31T21:47:35.359Z",
											"y": 100
										},
										{
											"x": "2021-01-31T21:47:40.388Z",
											"y": 100
										},
										{
											"x": "2021-01-31T21:47:45.299Z",
											"y": 100
										},
										{
											"x": "2021-01-31T21:47:50.317Z",
											"y": 100
										},
										{
											"x": "2021-01-31T21:47:55.318Z",
											"y": 100
										},
										{
											"x": "2021-01-31T21:48:00.475Z",
											"y": 100
										},
										{
											"x": "2021-01-31T21:48:05.498Z",
											"y": 100
										},
										{
											"x": "2021-01-31T21:48:10.525Z",
											"y": 100
										},
										{
											"x": "2021-01-31T21:48:15.502Z",
											"y": 100
										},
										{
											"x": "2021-01-31T21:48:20.555Z",
											"y": 100
										},
										{
											"x": "2021-01-31T21:48:25.476Z",
											"y": 100
										},
										{
											"x": "2021-01-31T21:48:30.469Z",
											"y": 100
										},
										{
											"x": "2021-01-31T21:48:35.351Z",
											"y": 100
										},
										{
											"x": "2021-01-31T21:48:40.398Z",
											"y": 100
										},
										{
											"x": "2021-01-31T21:49:22.674Z",
											"y": 100
										},
										{
											"x": "2021-01-31T21:49:27.688Z",
											"y": 100
										},
										{
											"x": "2021-01-31T21:49:32.606Z",
											"y": 100
										},
										{
											"x": "2021-01-31T21:49:37.613Z",
											"y": 100
										},
										{
											"x": "2021-01-31T21:49:42.631Z",
											"y": 100
										},
										{
											"x": "2021-01-31T21:49:47.679Z",
											"y": 100
										},
										{
											"x": "2021-01-31T21:49:52.669Z",
											"y": 100
										},
										{
											"x": "2021-01-31T21:49:57.685Z",
											"y": 100
										},
										{
											"x": "2021-01-31T21:50:02.611Z",
											"y": 100
										},
										{
											"x": "2021-01-31T21:50:07.638Z",
											"y": 100
										},
										{
											"x": "2021-01-31T21:50:12.647Z",
											"y": 100
										},
										{
											"x": "2021-01-31T21:50:17.658Z",
											"y": 100
										},
										{
											"x": "2021-01-31T21:50:22.674Z",
											"y": 100
										},
										{
											"x": "2021-01-31T21:50:27.706Z",
											"y": 100
										},
										{
											"x": "2021-01-31T21:50:32.615Z",
											"y": 100
										},
										{
											"x": "2021-01-31T21:50:37.643Z",
											"y": 100
										},
										{
											"x": "2021-01-31T21:50:42.642Z",
											"y": 100
										},
										{
											"x": "2021-01-31T21:50:47.660Z",
											"y": 100
										},
										{
											"x": "2021-01-31T21:50:52.687Z",
											"y": 100
										},
										{
											"x": "2021-01-31T21:50:57.712Z",
											"y": 100
										},
										{
											"x": "2021-01-31T21:51:02.620Z",
											"y": 100
										},
										{
											"x": "2021-01-31T21:51:07.647Z",
											"y": 100
										},
										{
											"x": "2021-01-31T21:51:12.680Z",
											"y": 100
										},
										{
											"x": "2021-01-31T21:51:17.682Z",
											"y": 100
										},
										{
											"x": "2021-01-31T21:51:22.690Z",
											"y": 100
										},
										{
											"x": "2021-01-31T21:51:27.718Z",
											"y": 100
										},
										{
											"x": "2021-01-31T21:51:32.642Z",
											"y": 100
										},
										{
											"x": "2021-01-31T21:51:37.655Z",
											"y": 100
										},
										{
											"x": "2021-01-31T21:51:42.676Z",
											"y": 100
										},
										{
											"x": "2021-01-31T21:51:47.684Z",
											"y": 100
										},
										{
											"x": "2021-01-31T21:51:52.691Z",
											"y": 100
										},
										{
											"x": "2021-01-31T21:51:57.624Z",
											"y": 100
										},
										{
											"x": "2021-01-31T21:52:02.888Z",
											"y": 100
										},
										{
											"x": "2021-01-31T21:52:07.904Z",
											"y": 100
										},
										{
											"x": "2021-01-31T21:52:12.756Z",
											"y": 100
										},
										{
											"x": "2021-01-31T21:52:17.942Z",
											"y": 100
										},
										{
											"x": "2021-01-31T21:52:22.936Z",
											"y": 100
										},
										{
											"x": "2021-01-31T21:52:27.689Z",
											"y": 100
										},
										{
											"x": "2021-01-31T21:52:32.615Z",
											"y": 100
										},
										{
											"x": "2021-01-31T21:52:37.733Z",
											"y": 100
										},
										{
											"x": "2021-01-31T21:52:42.671Z",
											"y": 100
										},
										{
											"x": "2021-01-31T21:52:47.931Z",
											"y": 100
										},
										{
											"x": "2021-01-31T21:52:52.812Z",
											"y": 100
										},
										{
											"x": "2021-01-31T21:52:57.875Z",
											"y": 100
										},
										{
											"x": "2021-01-31T21:53:02.809Z",
											"y": 100
										},
										{
											"x": "2021-01-31T21:53:07.792Z",
											"y": 100
										},
										{
											"x": "2021-01-31T21:53:12.910Z",
											"y": 100
										},
										{
											"x": "2021-01-31T21:53:17.830Z",
											"y": 100
										},
										{
											"x": "2021-01-31T21:53:22.844Z",
											"y": 100
										},
										{
											"x": "2021-01-31T21:53:27.608Z",
											"y": 100
										},
										{
											"x": "2021-01-31T21:53:32.734Z",
											"y": 100
										},
										{
											"x": "2021-01-31T21:53:37.782Z",
											"y": 100
										},
										{
											"x": "2021-01-31T21:53:42.904Z",
											"y": 100
										},
										{
											"x": "2021-01-31T21:53:47.916Z",
											"y": 100
										},
										{
											"x": "2021-01-31T21:53:52.842Z",
											"y": 100
										},
										{
											"x": "2021-01-31T21:53:57.801Z",
											"y": 100
										},
										{
											"x": "2021-01-31T21:54:02.776Z",
											"y": 100
										},
										{
											"x": "2021-01-31T21:54:07.898Z",
											"y": 100
										},
										{
											"x": "2021-01-31T21:54:12.657Z",
											"y": 100
										},
										{
											"x": "2021-01-31T21:54:17.678Z",
											"y": 100
										}
									]
								}
							],
							"xAxisTimeFormat": "HH:mm",
							"panelName": "Temperature/HeaterUtilization",
							"panelId": "panel_1",
							"type": "line-graph",
							"panelWidth": "100",
							"qos": 0,
							"panelMergeClass": "     ",
							"unit": "째/%",
							"hideLegend": false,
							"mqttType": "sub"
						},
						{
							"showReceivedTimeStamp": false,
							"showLatestMsgOnly": true,
							"hideTopic": true,
							"unit": " C",
							"panelName": "Temperature",
							"topic": "temperature",
							"fontSize": "30",
							"panelId": "panel_10",
							"type": "log",
							"logLength": 2,
							"panelWidth": "50",
							"qos": 0,
							"panelMergeClass": "    ",
							"mqttType": "sub"
						},
						{
							"showReceivedTimeStamp": false,
							"showLatestMsgOnly": true,
							"hideTopic": true,
							"unit": " %",
							"panelName": "HeaterUtilization",
							"topic": "heaterUtilization",
							"fontSize": "30",
							"panelId": "panel_21",
							"type": "log",
							"logLength": 2,
							"panelWidth": "50",
							"qos": 0,
							"panelMergeClass": "    ",
							"mqttType": "sub"
						},
						{
							"showReceivedTimeStamp": false,
							"showLatestMsgOnly": true,
							"hideTopic": true,
							"unit": " C",
							"panelName": "Temperature Error",
							"topic": "temperatureAboveTarget",
							"fontSize": "23",
							"panelId": "panel_22",
							"type": "log",
							"logLength": 2,
							"panelWidth": "50",
							"qos": 0,
							"panelMergeClass": "    ",
							"mqttType": "sub"
						},
						{
							"showReceivedTimeStamp": false,
							"showLatestMsgOnly": true,
							"hideTopic": true,
							"unit": " C",
							"panelName": "Temperature Change",
							"topic": "pastTemperatureChange",
							"fontSize": "23",
							"panelId": "panel_23",
							"type": "log",
							"logLength": 2,
							"panelWidth": "50",
							"qos": 0,
							"panelMergeClass": "    ",
							"mqttType": "sub"
						},
						{
							"panelName": "On/Off",
							"topic": "pidON/set",
							"payloadOn": "1",
							"payloadOff": "0",
							"hasCustomIcon": false,
							"iconOn": "flash_on",
							"iconColorOn": "#9E9E9E",
							"iconOff": "flash_off",
							"iconColorOff": "#9E9E9E",
							"panelId": "panel_6",
							"type": "switch",
							"panelWidth": "25",
							"retain": true,
							"qos": 0,
							"seperateSubscribeTopic": "pidON",
							"mqttType": "pubsub"
						},
						{
							"iconOn": "hot_cup",
							"iconColorOn": "#5fe000",
							"iconOff": "heater",
							"iconColorOff": "#e71919",
							"topic": "brewReady",
							"payloadOn": "1",
							"payloadOff": "0",
							"panelName": "Status",
							"panelId": "panel_2",
							"type": "led",
							"panelWidth": "50",
							"qos": 0,
							"panelMergeClass": "     ",
							"mqttType": "sub"
						},
						{
							"iconOn": "led",
							"iconColorOn": "#5fe000",
							"iconOff": "led",
							"iconColorOff": "#9E9E9E",
							"topic": "brewDetected",
							"payloadOn": "1",
							"payloadOff": "0",
							"panelName": "Brewing",
							"panelId": "panel_3",
							"type": "led",
							"panelWidth": "25",
							"qos": 0,
							"panelMergeClass": "     ",
							"mqttType": "sub"
						},
						{
							"panelName": "SetPoint",
							"topic": "setPoint/set",
							"seperateSubscribeTopic": "setPoint",
							"payloadMax": 97.5,
							"payloadMin": 90.5,
							"unit": " C",
							"orientation": "horizontal",
							"retain": true,
							"panelId": "panel_8",
							"type": "slider",
							"panelWidth": "66",
							"qos": 0,
							"confirmBeforePublish": false,
							"confirmationMessage": "Set",
							"panelMergeClass": "merge-left    ",
							"mqttType": "pubsub"
						},
						{
							"panelName": "Brewtime",
							"topic": "brewtime/set",
							"seperateSubscribeTopic": "brewtime",
							"payloadMin": 0,
							"payloadMax": 45,
							"unit": " Sec",
							"confirmBeforePublish": false,
							"retain": true,
							"panelId": "panel_9",
							"type": "slider",
							"panelWidth": "66",
							"orientation": "horizontal",
							"qos": 0,
							"confirmationMessage": "Ok?",
							"panelMergeClass": "   merge-bottom",
							"mqttType": "pubsub"
						},
						{
							"panelName": "Preinfusion",
							"titleAlignment": "center",
							"panelId": "panel_15",
							"type": "layout-decorator",
							"fontSize": "20",
							"panelWidth": "100",
							"mqttType": "none"
						},
						{
							"panelName": "Preinfusion",
							"topic": "preinfusion/set",
							"seperateSubscribeTopic": "preinfusion",
							"payloadMin": 0,
							"payloadMax": 10,
							"unit": " Sec",
							"confirmBeforePublish": false,
							"retain": true,
							"panelId": "panel_11",
							"type": "slider",
							"panelWidth": "66",
							"orientation": "horizontal",
							"qos": 0,
							"confirmationMessage": "Ok?",
							"panelMergeClass": "      ",
							"mqttType": "pubsub"
						},
						{
							"panelName": "PreinfusionPause",
							"topic": "preinfusionpause/set",
							"seperateSubscribeTopic": "preinfusionpause",
							"payloadMin": 0,
							"payloadMax": 10,
							"unit": " Sec",
							"confirmBeforePublish": false,
							"retain": true,
							"panelId": "panel_12",
							"type": "slider",
							"panelWidth": "66",
							"orientation": "horizontal",
							"qos": 0,
							"confirmationMessage": "Ok?",
							"mqttType": "pubsub"
						},
						{
							"panelName": "BrewDetection",
							"titleAlignment": "center",
							"panelId": "panel_13",
							"type": "layout-decorator",
							"fontSize": "20",
							"panelWidth": "100",
							"mqttType": "none"
						},
						{
							"panelName": "Sensitivity",
							"topic": "brewDetectionSensitivity/set",
							"seperateSubscribeTopic": "brewDetectionSensitivity",
							"payloadMin": 0.4,
							"payloadMax": 1.4,
							"unit": " C",
							"confirmBeforePublish": false,
							"retain": true,
							"panelId": "panel_14",
							"type": "slider",
							"panelWidth": "66",
							"orientation": "horizontal",
							"qos": 0,
							"confirmationMessage": "Ok?",
							"panelMergeClass": "    ",
							"mqttType": "pubsub"
						},
						{
							"panelName": "Power",
							"topic": "brewDetectionPower/set",
							"seperateSubscribeTopic": "brewDetectionPower",
							"payloadMin": 0,
							"payloadMax": 100,
							"unit": " %",
							"confirmBeforePublish": false,
							"retain": true,
							"panelId": "panel_16",
							"type": "slider",
							"panelWidth": "66",
							"orientation": "horizontal",
							"qos": 0,
							"confirmationMessage": "Ok?",
							"panelMergeClass": "    ",
							"mqttType": "pubsub"
						},
						{
							"panelName": "SteadyPower (Auto)",
							"titleAlignment": "center",
							"panelId": "panel_17",
							"type": "layout-decorator",
							"fontSize": "20",
							"panelWidth": "100",
							"mqttType": "none"
						},
						{
							"panelName": "Power",
							"topic": "steadyPower/set",
							"seperateSubscribeTopic": "steadyPower",
							"payloadMin": 0,
							"payloadMax": 15.1,
							"unit": " %",
							"confirmBeforePublish": false,
							"retain": true,
							"panelId": "panel_18",
							"type": "slider",
							"panelWidth": "66",
							"orientation": "horizontal",
							"qos": 0,
							"confirmationMessage": "Ok?",
							"panelMergeClass": "    ",
							"mqttType": "pubsub"
						},
						{
							"panelName": "PowerOffset",
							"topic": "steadyPowerOffset/set",
							"seperateSubscribeTopic": "steadyPowerOffset",
							"payloadMin": 0,
							"payloadMax": 10.1,
							"unit": " %",
							"confirmBeforePublish": false,
							"retain": true,
							"panelId": "panel_19",
							"type": "slider",
							"panelWidth": "66",
							"orientation": "horizontal",
							"qos": 0,
							"confirmationMessage": "Ok?",
							"panelMergeClass": "    ",
							"mqttType": "pubsub"
						},
						{
							"panelName": "PowerOffsetTime",
							"topic": "steadyPowerOffsetTime/set",
							"seperateSubscribeTopic": "steadyPowerOffsetTime",
							"payloadMin": 1,
							"payloadMax": 1200,
							"unit": " Sec",
							"confirmBeforePublish": false,
							"retain": true,
							"panelId": "panel_20",
							"type": "slider",
							"panelWidth": "66",
							"orientation": "horizontal",
							"qos": 0,
							"confirmationMessage": "Ok?",
							"panelMergeClass": "    ",
							"mqttType": "pubsub"
						},
						{
							"panelName": "starttemp",
							"topic": "starttemp/set",
							"seperateSubscribeTopic": "starttemp",
							"retain": true,
							"payloadMin": 70,
							"payloadMax": 90,
							"panelId": "panel_26",
							"type": "slider",
							"panelWidth": "66",
							"orientation": "horizontal",
							"qos": 0,
							"mqttType": "pubsub"
						},
						{
							"panelName": "Actions",
							"titleAlignment": "center",
							"panelId": "panel_31",
							"type": "layout-decorator",
							"mqttType": "none",
							"fontSize": "20",
							"panelWidth": "100"
						},
						{
							"panelName": "Brewing",
							"topic": "actions/BREWING",
							"payloadOn": "1",
							"payloadOff": "0",
							"panelId": "panel_32",
							"type": "switch",
							"mqttType": "pubsub",
							"panelWidth": "66",
							"retain": false,
							"qos": 0
						},
						{
							"panelName": "Steaming",
							"topic": "actions/STEAMING",
							"payloadOn": "1",
							"payloadOff": "0",
							"hasCustomIcon": false,
							"iconOn": "switch_on",
							"iconColorOn": "#9E9E9E",
							"iconOff": "switch_off",
							"iconColorOff": "#9E9E9E",
							"panelId": "panel_29",
							"type": "switch",
							"mqttType": "pubsub",
							"panelWidth": "66",
							"retain": false,
							"qos": 0
						},
						{
							"panelName": "Cleaning",
							"topic": "actions/CLEANING",
							"payloadOn": "1",
							"payloadOff": "0",
							"panelId": "panel_30",
							"type": "switch",
							"mqttType": "pubsub",
							"panelWidth": "66",
							"retain": false,
							"qos": 0
						},
						{
							"panelName": "Events",
							"titleAlignment": "center",
							"fontSize": "20",
							"panelId": "panel_25",
							"type": "layout-decorator",
							"panelWidth": "100",
							"mqttType": "none"
						},
						{
							"showReceivedTimeStamp": false,
							"panelName": "Events",
							"topic": "events",
							"panelId": "panel_24",
							"type": "log",
							"logLength": 10,
							"panelWidth": "100",
							"qos": 0,
							"hideTopic": true,
							"showLatestMsgOnly": false,
							"fontSize": "20",
							"maxPersistence": 10,
							"mqttType": "sub"
						}
					],
					"lockPanels": false
				}
			],
			"dashboardQuickAccess": false,
			"username": "MYUSER",
			"password": "MYPASS"
		}
	],
	"appTheme": "dark",
	"runInBackground": false,
	"wakeLock": false,
	"displayOrientation": "portrait"
}